README.md
setup.py
app/__init__.py
app/forms.py
app/models.py
app/routes.py
converge4.egg-info/PKG-INFO
converge4.egg-info/SOURCES.txt
converge4.egg-info/dependency_links.txt
converge4.egg-info/not-zip-safe
converge4.egg-info/top_level.txt